Workbook

Sheet 機能一覧
P1: 自動化対象 | S1: 修正フラグ
A2: ID | B2: 画面 | C2: 機能 | F2: 備考 | G2: 重要度(*1) | H2: バリエーション | I2: 備考 | J2: 前提条件 | K2: 確認手順 | L2: 確認内容 | M2: 実施者 | N2: 結果 | P2: 関数 | Q2: 値のみ ※誤修正した場合のバックアップ | S2: 追加 | T2: 修正
A3: 1 | B3: ログイン | C3: ログイン | D3: 多要素認証(無効) | G3: A | J3: ・ログイン画面を表示していること ・多要素認証を無効にしているアカウントがあること | K3: 1.ズメーンに登録済みのメールアドレスとパスワードを入力する 2.「続ける」を押下する | L3: ・入力したアカウントでログインできること | M3: Auto | N3: 自動化 | P3: =IF(ISNUMBER(SEARCH("Auto",M3)),"〇","×") -> 〇 | Q3: 〇
A4: =A3+1 -> 2 | B4: ログイン | C4: ログイン | D4: 多要素認証(有効) | G4: A | J4: ・ログイン画面を表示していること ・多要素認証を有効にしているアカウントがあること | K4: 1.ズメーンに登録済みのメールアドレスとパスワードを入力する 2.「続ける」を押下する 3.認証アプリを使用して、ワンタイムコードの入力を行う 4.「続ける」を押下する 5.「続ける」を押下する | L4: ・入力したアカウントでログインできること | M4: Auto | N4: 自動化 | P4: =IF(ISNUMBER(SEARCH("Auto",M4)),"〇","×") -> 〇 | Q4: 〇
A5: =A4+1 -> 3 | B5: ログイン | C5: パスワードリセット | G5: B | I5: ※パスワードリセット宛のメールが届くため、受信を確認できるメールアドレスで実施する | J5: ・ログイン画面を表示していること | K5: 1.「パスワードをお忘れですか？」を押下する 2.ズメーンに登録済みのメールアドレスを入力する 3.「続ける」を押下する 4.受信した【ズメーン】パスワードの変更の「こちら」を押下する 5.新しいパスワードと新しいパスワードの再入力に同値を入力する 6.「パスワードのリセット」を押下する 7.メールアドレスと変更したパスワードでズメーンにログインを行う | L5: ・入力したアカウントでログインできること | M5: Auto | N5: 自動化 | P5: =IF(ISNUMBER(SEARCH("Auto",M5)),"〇","×") -> 〇 | Q5: 〇
A6: =A5+1 -> 4 | B6: フリーワード検索 | C6: 図面⇔ファイル切り替え | G6: A | J6: ・図面フリーワード検索画面を表示していること | K6: 1.ラジオボタンの「ファイル」を押下する 2.ラジオボタンの「図面」を押下する | L6: ・図面とファイルのフリーワード検索が切り替わること | N6: 未実施 | P6: =IF(ISNUMBER(SEARCH("Auto",M6)),"〇","×") -> × | Q6: ×
A7: =A6+1 -> 5 | B7: フリーワード検索 | C7: 図面 | D7: 検索 | G7: A | I7: ※入力した内容による検索パターンはチケットテスト時に行う | J7: ・図面フリーワード検索画面を表示していること | K7: 1.任意の値を入力する | L7: ・検索内容にヒットした図面が表示されること | N7: 未実施 | P7: =IF(ISNUMBER(SEARCH("Auto",M7)),"〇","×") -> × | Q7: ×
A8: =A7+1 -> 6 | B8: フリーワード検索 | C8: 図面 | D8: 絞り込み | G8: A | J8: 同上 | K8: 2.「絞り込み」を押下する 3.任意の期間を選択する | L8: ・選択した期間の登録日の図面のみ表示されること | N8: 未実施 | P8: =IF(ISNUMBER(SEARCH("Auto",M8)),"〇","×") -> × | Q8: ×
A9: =A8+1 -> 7 | B9: フリーワード検索 | C9: 図面 | D9: 並び順 | G9: A | J9: 同上 | K9: 4.「並び順」を押下する 5.任意の順を選択する | L9: ・選択した並び順の通りに表示されること | N9: 未実施 | P9: =IF(ISNUMBER(SEARCH("Auto",M9)),"〇","×") -> × | Q9: ×
A10: =A9+1 -> 8 | B10: フリーワード検索 | C10: ファイル | D10: 検索 | G10: A | I10: ※入力した内容による検索パターンはチケットテスト時に行う | J10: ・ファイルフリーワード検索画面を表示していること | K10: 1.任意の値を入力する | L10: ・検索内容にヒットしたファイルが表示されること | N10: 未実施 | P10: =IF(ISNUMBER(SEARCH("Auto",M10)),"〇","×") -> × | Q10: ×
A11: =A10+1 -> 9 | B11: フリーワード検索 | C11: ファイル | D11: 絞り込み | G11: A | J11: 同上 | K11: 2.「絞り込み」を押下する 3.任意の期間を選択する 4.任意の種別を選択する | L11: ・選択した期間の登録日と種別のファイルのみ表示されること | N11: 未実施 | P11: =IF(ISNUMBER(SEARCH("Auto",M11)),"〇","×") -> × | Q11: ×
A12: =A11+1 -> 10 | B12: フリーワード検索 | C12: ファイル | D12: 並び順 | G12: A | J12: 同上 | K12: 5.「並び順」を押下する 6.任意の順を選択する | L12: ・選択した並び順の通りに表示されること | N12: 未実施 | P12: =IF(ISNUMBER(SEARCH("Auto",M12)),"〇","×") -> × | Q12: ×
A13: =A12+1 -> 11 | B13: 図面一覧 | C13: 一括操作 | D13: 選択 | E13: 単一選択 | G13: A | J13: ・図面一覧画面を表示していること | K13: 1.「一括操作」を押下する 2.任意の図面を押下する 3.手順2と同様の図面を押下する | L13: ・図面の選択/未選択が切り替わること | N13: 未実施 | P13: =IF(ISNUMBER(SEARCH("Auto",M13)),"〇","×") -> × | Q13: ×
A14: =A13+1 -> 12 | B14: 図面一覧 | C14: 一括操作 | D14: 選択 | E14: 全選択 | G14: A | J14: ・図面一覧画面を表示していること | K14: 1.「一括操作」を押下する 2.「全選択」を押下する 3.「全選択」を押下する | L14: ・同ページ内の図面の選択/未選択が切り替わること | N14: 未実施 | P14: =IF(ISNUMBER(SEARCH("Auto",M14)),"〇","×") -> × | Q14: ×
A15: =A14+1 -> 13 | B15: 図面一覧 | C15: 一括操作 | D15: 新規案件作成 | E15: すべての行に反映 | G15: A | J15: 同上 | K15: 1.「一括操作」を押下する 2.任意の図面を押下する 3.「新規案件作成」を押下する 4.最上部の行に任意の値を入力・選択する 5.「すべての行に反映」を押下する | L15: ・最上部の行の値がすべての案件に反映されること | N15: 未実施 | P15: =IF(ISNUMBER(SEARCH("Auto",M15)),"〇","×") -> × | Q15: ×
A16: =A15+1 -> 14 | B16: 図面一覧 | C16: 一括操作 | D16: 新規案件作成 | E16: 手入力 | G16: A | J16: 同上 | K16: 6.案件行に任意の値を入力・選択する | L16: ・入力・選択した通りに値が入力できること | N16: 未実施 | P16: =IF(ISNUMBER(SEARCH("Auto",M16)),"〇","×") -> × | Q16: ×
A17: =A16+1 -> 15 | B17: 図面一覧 | C17: 一括操作 | D17: 新規案件作成 | G17: A | I17: ※すべて同一のステータスの場合は該当タブ、それ以外の場合は「すべてタブ」 | J17: 同上 | K17: 7.「案件を作成する」を押下する 8.「案件一覧に移動する」を押下する | L17: ・入力した値の通りに新規案件が作成されること ・案件一覧画面に遷移すること | N17: 未実施 | P17: =IF(ISNUMBER(SEARCH("Auto",M17)),"〇","×") -> × | Q17: ×
A18: =A17+1 -> 16 | B18: 図面一覧 | C18: 一括操作 | D18: ファイル追加 | G18: B | J18: ・図面一覧画面を表示していること | K18: 1.「一括操作」を押下する 2.任意の図面を押下する 3.「ファイル追加」を押下する 4.図面と関連資料で任意のファイルを選択する 5.「保存する」を押下する | L18: ・選択した図面にファイルの追加をできること | N18: 未実施 | P18: =IF(ISNUMBER(SEARCH("Auto",M18)),"〇","×") -> × | Q18: ×
A19: =A18+1 -> 17 | B19: 図面一覧 | C19: 一括操作 | D19: ファイル追加 | G19: B | I19: タブレットで実施 ※実施するOS/機種については別途相談 | J19: ・図面一覧画面を表示していること | K19: 1.「一括操作」を押下する 2.任意の図面を押下する 3.「ファイル追加」を押下する 4.「ファイルを選択」を押下する 5.「写真ライブラリ」を押下する 6.任意の写真を選択する 7.「保存する」を押下する | L19: ・写真ライブラリからアップロードできること | N19: 未実施 | P19: =IF(ISNUMBER(SEARCH("Auto",M19)),"〇","×") -> × | Q19: ×
A20: =A19+1 -> 18 | B20: 図面一覧 | C20: 一括操作 | D20: ファイル追加 | E20: 写真を撮る(タブレット) ※関連資料は録画も | G20: B | I20: タブレットで実施 ※実施するOS/機種については別途相談 | J20: ・図面一覧画面を表示していること | K20: 1.「一括操作」を押下する 2.任意の図面を押下する 3.「ファイル追加」を押下する 4.「ファイルを選択」を押下する 5.「写真を撮る」を押下する 6.写真の撮影を行う 7.「保存する」を押下する | L20: ・撮影した写真をアップロードできること | N20: 未実施 | P20: =IF(ISNUMBER(SEARCH("Auto",M20)),"〇","×") -> × | Q20: ×
A21: =A20+1 -> 19 | B21: 図面一覧 | C21: 一括操作 | D21: 図面項目編集 | G21: B | J21: ・図面一覧画面を表示していること | K21: 1.「一括操作」を押下する 2.任意の図面を押下する 3.「図面項目編集」を押下する 4.任意の項目を選択する 5.「次へ」を押下する 6.任意の値を入力/選択する 7.「保存する」を押下する | L21: ・変更内容が反映されること | N21: 未実施 | P21: =IF(ISNUMBER(SEARCH("Auto",M21)),"〇","×") -> × | Q21: ×
A22: =A21+1 -> 20 | B22: 図面一覧 | C22: 一括操作 | D22: 連続書込 | G22: A | J22: ・図面一覧画面を表示していること | K22: 1.「一括操作」を押下する 2.任意の図面を複数押下する 3.「連続書込」を押下する 4.任意の書き込みを行う 5.書き込んだオブジェクトをコピーする(ctrl + c or cmd + c) 6.「新しいファイルとして保存して次へ」を押下する 7.コピーしたオブジェクトををペーストする(ctrl + v or cmd + v) 8.「新しいファイルとして保存して終了」を押下する | L22: ・ファイルを跨いだオブジェクトのコピペができ、書きこも保存後のプレビューが正常に表示されること | N22: 未実施 | P22: =IF(ISNUMBER(SEARCH("Auto",M22)),"〇","×") -> × | Q22: × | S22: 〇
A23: =A22+1 -> 21 | B23: 図面一覧 | C23: 一括操作 | D23: 最新図面印刷 | G23: B | J23: ・図面一覧画面を表示していること | K23: 1.「一括操作」を押下する 2.任意の図面を押下する 3.「最新図面印刷」を押下する | L23: ・選択した図面の印刷プレビューが表示されること | N23: 未実施 | P23: =IF(ISNUMBER(SEARCH("Auto",M23)),"〇","×") -> × | Q23: ×
A24: =A23+1 -> 22 | B24: 図面一覧 | C24: 一括操作 | D24: 最新図面ダウンロード | G24: B | J24: ・図面一覧画面を表示していること | K24: 1.「一括操作」を押下する 2.任意の図面を押下する 3.「最新図面ダウンロード」を押下する | L24: ・選択した図面の最新図面がすべてダウンロードできること | N24: 未実施 | P24: =IF(ISNUMBER(SEARCH("Auto",M24)),"〇","×") -> × | Q24: ×
A25: =A24+1 -> 23 | B25: 図面一覧 | C25: 一括操作 | D25: 一括削除 | G25: B | J25: ・図面一覧画面を表示していること | K25: 1.「一括操作」を押下する 2.任意の図面を押下する 3.「削除」を押下する 4."delete"と入力する 5.「削除する」を押下する | L25: ・選択した図面をすべて削除できること | N25: 未実施 | P25: =IF(ISNUMBER(SEARCH("Auto",M25)),"〇","×") -> × | Q25: ×
A26: =A25+1 -> 24 | B26: 図面一覧 | C26: 新しい図面を追加 | D26: ファイル選択(ボタン) | E26: 組図保存なし | F26: ※他画面でのファイル追加と合わせてファイル形式を網羅できるようにする？ | G26: A | H26: PDF AI 2D-CAD：DXF, DWG 画像：JPG, JPEG, JPE, BMP, HEIC, HEIF, GIF, PNG, TIF, TIFF, SVG | I26: ※図面詳細画面とファイル形式をわけて実施 | J26: ・図面一覧画面を表示していること ・自動登録しない、AIにおまかせ、ファイル名から登録で設定している項目があること | K26: 1.「新しい図面を追加」を押下する 2.ファイルを選択する 3.図面基本項目、図面詳細項目に任意の値を入力する 4.「さらにファイルを選択」を押下する 5.任意のファイルを選択する 6.「保存する」を押下する | L26: ・新しい図面を追加でき、入力した項目が反映されていること ・自動登録設定に応じた内容が入力・設定されていること ※図面詳細項目の文字項目に登録データのリストが表示されること | N26: 未実施 | P26: =IF(ISNUMBER(SEARCH("Auto",M26)),"〇","×") -> × | Q26: × | T26: 〇
A27: =A26+1 -> 25 | B27: 図面一覧 | C27: 新しい図面を追加 | D27: ドラック＆ドロップ | E27: 組図保存あり | F27: 同上 | G27: A | H27: 同上 | I27: 同上 | J27: ・図面一覧画面を表示していること | K27: 1.「新しい図面を追加」を押下する 2.ドラック＆ドロップ操作で2ファイル以上追加する 3.図面基本項目、図面詳細項目に任意の値を入力する 4.「組図として保存する」を押下する 5.任意の図面を選択する 6.「組図として保存する」を押下する | L27: ・新しい図面を追加でき、入力した項目が反映されていること ・自動登録設定に応じた内容が入力・設定されていること ・図面詳細の組図タブに遷移し、選択した図面が親図で他の図面が子図として追加されること | N27: 未実施 | P27: =IF(ISNUMBER(SEARCH("Auto",M27)),"〇","×") -> × | Q27: × | T27: 〇
A28: =A27+1 -> 26 | B28: 図面一覧 | C28: 新しい図面を追加 | D28: 写真ライブラリ(スマホ、タブレット) | G28: A | I28: スマホ、タブレットで実施 ※実施するOS/機種については別途相談 | J28: ・図面一覧画面を表示していること | K28: 1.「新しい図面を追加」を押下する 2.「ファイルを選択」を押下する 3.「写真ライブラリ」を押下する 4.任意の写真を選択する 5.「保存する」を押下する | L28: ・写真ライブラリからアップロードできること | N28: 未実施 | P28: =IF(ISNUMBER(SEARCH("Auto",M28)),"〇","×") -> × | Q28: ×
A29: =A28+1 -> 27 | B29: 図面一覧 | C29: 新しい図面を追加 | D29: 写真を撮る(スマホ、タブレット) | G29: A | I29: スマホ、タブレットで実施 ※実施するOS/機種については別途相談 | J29: ・図面一覧画面を表示していること | K29: 1.「新しい図面を追加」を押下する 2.「ファイルを選択」を押下する 3.「写真を撮る」を押下する 4.写真の撮影を行う 5.「保存する」を押下する | L29: ・撮影した写真をアップロードできること | N29: 未実施 | P29: =IF(ISNUMBER(SEARCH("Auto",M29)),"〇","×") -> × | Q29: ×
A30: =A29+1 -> 28 | B30: 図面一覧 | C30: 新しい図面を追加 | D30: ファイルを選択(スマホ、タブレット) | G30: A | I30: スマホ、タブレットで実施 ※実施するOS/機種については別途相談 | J30: ・図面一覧画面を表示していること | K30: 1.「新しい図面を追加」を押下する 2.「ファイルを選択」を押下する 3.「ファイルを選択」を押下する 4.任意のファイルを選択する 5.「保存する」を押下する | L30: ・ファイルからアップロードできること | N30: 未実施 | P30: =IF(ISNUMBER(SEARCH("Auto",M30)),"〇","×") -> × | Q30: ×
A31: =A30+1 -> 29 | B31: 図面一覧 | C31: PDFを分割+書き込み | G31: A | H31: PDF | J31: ・図面一覧画面を表示していること | K31: 1.「新しい図面を追加」を押下する 2.PDFファイルを選択する 3.「分割」を押下する 4.任意の分割を行う 5.任意のページ「このページを複製」を押下する 6.「書き込み」を押下する 7.任意の書き込みを行う 8.「+追加」を押下する 9.「保存する」を押下する 10.「分割された図面を新規追加」を押下する 11.図面基本項目、図面詳細項目に任意の値を入力する 12.「保存する」を押下する | L31: ・新しい図面を追加でき、入力した項目が反映されていること ・分割/書き込みが正しく反映されていること | N31: 未実施 | P31: =IF(ISNUMBER(SEARCH("Auto",M31)),"〇","×") -> × | Q31: × | T31: 〇
A32: =A31+1 -> 30 | B32: 図面一覧 | C32: 検索 | G32: A | J32: ・図面一覧画面を表示していること | K32: 1.検索内容の入力/選択を行う | L32: ・条件に一致する図面のみ表示されること | N32: 未実施 | P32: =IF(ISNUMBER(SEARCH("Auto",M32)),"〇","×") -> × | Q32: ×
A33: =A32+1 -> 31 | B33: 図面一覧 | C33: 検索 | D33: 画面更新 | G33: A | J33: 同上 | K33: 2.画面の更新を行う | L33: ・検索条件が保持され、正しい検索内容が表示されること | N33: 未実施 | P33: =IF(ISNUMBER(SEARCH("Auto",M33)),"〇","×") -> × | Q33: ×
A34: =A33+1 -> 32 | B34: 図面一覧 | C34: 並び替え | G34: A | H34: 登録日順、最終更新日時順、図番順、納品日(日付項目) | J34: ・図面一覧画面を表示していること | K34: 1.並び替えから表示順を選択する | L34: ・選択した並び順の通りに表示されること | N34: 未実施 | P34: =IF(ISNUMBER(SEARCH("Auto",M34)),"〇","×") -> × | Q34: ×
A35: =A34+1 -> 33 | B35: 図面一覧 | C35: 表示数 | G35: A | H35: 25件、50件、100件 | J35: ・図面一覧画面を表示していること | K35: 1.表示数から任意の件数を選択する | L35: ・選択した通りの件数で表示されること | N35: 未実施 | P35: =IF(ISNUMBER(SEARCH("Auto",M35)),"〇","×") -> × | Q35: ×
A36: =A35+1 -> 34 | B36: 図面一覧 | C36: 図面の未読管理 | D36: 未読 | G36: A | J36: ・図面一覧画面を表示していること | K36: 1.新規図面のアップロードを行う | L36: ・新規図面にNewアイコンが付くこと | N36: 未実施 | P36: =IF(ISNUMBER(SEARCH("Auto",M36)),"〇","×") -> × | Q36: ×
A37: =A36+1 -> 35 | B37: 図面一覧 | C37: 図面の未読管理 | D37: 未閲覧の新規図面のみ表示 | G37: A | J37: 同上 | K37: 2.「未閲覧の新規図面のみ表示」のチェックをONにする | L37: ・未読の図面のみ表示されること | N37: 未実施 | P37: =IF(ISNUMBER(SEARCH("Auto",M37)),"〇","×") -> × | Q37: ×
A38: =A37+1 -> 36 | B38: 図面一覧 | C38: 図面の未読管理 | D38: 既読 | G38: A | J38: 同上 | K38: 3.任意の図面を押下する 4.「←」を押下する | L38: ・該当図面が既読になること(Newアイコンが消える) | N38: 未実施 | P38: =IF(ISNUMBER(SEARCH("Auto",M38)),"〇","×") -> × | Q38: ×
A39: =A38+1 -> 37 | B39: 図面一覧 | C39: プレビュー表示 | G39: A | J39: ・図面一覧画面のリスト表示タブを表示していること | K39: 1.「プレビュー」を押下する | L39: ・プレビュー表示に切り替わること | N39: 未実施 | P39: =IF(ISNUMBER(SEARCH("Auto",M39)),"〇","×") -> × | Q39: ×
A40: =A39+1 -> 38 | B40: 図面一覧 | C40: リスト表示 | G40: A | J40: ・図面一覧画面のプレビュー表示タブを表示していること | K40: 1.「リスト」を押下する | L40: ・リスト表示に切り替わること | N40: 未実施 | P40: =IF(ISNUMBER(SEARCH("Auto",M40)),"〇","×") -> × | Q40: ×
A41: =A40+1 -> 39 | B41: 図面一覧 | C41: リスト表示 | D41: 図面リンク | F41: ※0件の場合、"0"ではなく"-"表示 | G41: A | J41: ・図面一覧画面のリスト表示タブを表示していること | K41: 1.図面の件数リンクを押下する | L41: ・押下した図面の図面タブが別タブで開くこと | N41: 未実施 | P41: =IF(ISNUMBER(SEARCH("Auto",M41)),"〇","×") -> × | Q41: ×
A42: =A41+1 -> 40 | B42: 図面一覧 | C42: リスト表示 | D42: 関連資料リンク | F42: ※0件の場合、"0"ではなく"-"表示 | G42: A | J42: ・図面一覧画面のリスト表示タブを表示していること | K42: 1.関連資料の件数リンクを押下する | L42: ・押下した図面の該当の関連資料タブが別タブで開くこと | N42: 未実施 | P42: =IF(ISNUMBER(SEARCH("Auto",M42)),"〇","×") -> × | Q42: ×
A43: =A42+1 -> 41 | B43: 図面一覧 | C43: CSVダウンロード | G43: B | J43: ・図面一覧画面を表示していること | K43: 1.「…」を押下する 2.「CSVダウンロード」を押下する | L43: ・表示されている図面一覧のCSVダウンロードができること | N43: 未実施 | P43: =IF(ISNUMBER(SEARCH("Auto",M43)),"〇","×") -> × | Q43: ×
A44: =A43+1 -> 42 | B44: 図面一覧 | C44: xlsxで一括編集 | D44: エクスポート | G44: A | J44: ・図面一覧画面を表示していること | K44: 1.「…」を押下する 2.「エクセルで図面を一括編集」を押下する 3.「ダウンロード」を押下する | L44: ・編集用のエクセルファイルをダウンロードできること | N44: 未実施 | P44: =IF(ISNUMBER(SEARCH("Auto",M44)),"〇","×") -> × | Q44: ×
A45: =A44+1 -> 43 | B45: 図面一覧 | C45: xlsxで一括編集 | D45: インポート | G45: A | I45: ※正常値でアップロード後にエラーにならないファイルで確認する ※件数が多いと、すべての更新～メール受信までに時間がかかるので要注意 | J45: 同上 | K45: 4.ダウンロードしたエクセルファイルを編集し、アップロードを行う | L45: ・エクセルインポートの結果がメールで届き、図面の情報が更新されていること | N45: 未実施 | P45: =IF(ISNUMBER(SEARCH("Auto",M45)),"〇","×") -> × | Q45: ×
A46: =A45+1 -> 44 | B46: 図面一覧 | C46: ページング | G46: A | J46: ・図面一覧画面を表示していること | K46: 1.画面下部の数字、「<」、「>」を押下する | L46: ・図面一覧のページングができること | N46: 未実施 | P46: =IF(ISNUMBER(SEARCH("Auto",M46)),"〇","×") -> × | Q46: ×
A47: =A46+1 -> 45 | B47: 図面詳細 (「図面・資料」タブ)_共通 | C47: ファイル移動 | D47: タブ内 | G47: B | J47: ・図面詳細画面(「図面・資料」タブ)を表示していること | K47: 1.任意の図面をタブ内で移動を行う | L47: ・タブ内でファイルの移動ができること | N47: 未実施 | P47: =IF(ISNUMBER(SEARCH("Auto",M47)),"〇","×") -> × | Q47: ×
A48: =A47+1 -> 46 | B48: 図面詳細 (「図面・資料」タブ)_共通 | C48: ファイル移動 | D48: タブ間 | G48: B | J48: ・図面詳細画面(「図面・資料」タブ)を表示していること | K48: 1.任意の図面をタブ間で移動を行う | L48: ・タブ間でファイルの移動ができること | N48: 未実施 | P48: =IF(ISNUMBER(SEARCH("Auto",M48)),"〇","×") -> × | Q48: ×
A49: =A48+1 -> 47 | B49: 図面詳細 (「図面・資料」タブ)_共通 | C49: 図面一覧への戻り遷移 | D49: プレビュー | E49: 検索なし | G49: A | J49: ・図面詳細画面(「図面・資料」タブ)を表示していること ・図面一覧画面「プレビュー」タブから検索なしで遷移していること | K49: 1.「←図面一覧」を押下する | L49: ・図面一覧画面「プレビュー」タブに遷移し、選択した図面位置までスクロールされていること | N49: 未実施 | O49: 基本的にはOKだが残バグあり | P49: =IF(ISNUMBER(SEARCH("Auto",M49)),"〇","×") -> × | Q49: × | R49: プレビュー⇔リストに切り替え後に図面詳細への遷移では発生します！ →確認済
A50: =A49+1 -> 48 | B50: 図面詳細 (「図面・資料」タブ)_共通 | C50: 図面一覧への戻り遷移 | D50: プレビュー | E50: 検索あり | G50: A | J50: ・図面詳細画面(「図面・資料」タブ)を表示していること ・図面一覧画面「プレビュー」タブから検索ありで遷移していること | K50: 1.「←図面一覧」を押下する | L50: ・図面一覧画面「プレビュー」タブに遷移し、選択した図面位置までスクロールされていること ・図面一覧画面の検索条件が保持されていること | N50: 未実施 | O50: 基本的にはOKだが残バグあり | P50: =IF(ISNUMBER(SEARCH("Auto",M50)),"〇","×") -> × | Q50: × | R50: プレビュー⇔リストに切り替え後に図面詳細への遷移では発生します！ →確認済
A51: =A50+1 -> 49 | B51: 図面詳細 (「図面・資料」タブ)_共通 | C51: 図面一覧への戻り遷移 | D51: リスト | E51: 検索なし | G51: A | J51: ・図面詳細画面(「図面・資料」タブ)を表示していること ・図面一覧画面「リスト」タブから検索なしで遷移していること | K51: 1.「←図面一覧」を押下する | L51: ・図面一覧画面「リスト」タブに遷移すること ・図面一覧画面の検索条件が保持されていること | N51: 未実施 | O51: 基本的にはOKだが残バグあり | P51: =IF(ISNUMBER(SEARCH("Auto",M51)),"〇","×") -> × | Q51: × | R51: プレビュー⇔リストに切り替え後に図面詳細への遷移では発生します！ →確認済
A52: =A51+1 -> 50 | B52: 図面詳細 (「図面・資料」タブ)_共通 | C52: 図面一覧への戻り遷移 | D52: リスト | E52: 検索あり | G52: A | J52: ・図面詳細画面(「図面・資料」タブ)を表示していること ・図面一覧画面「リスト」タブから検索ありで遷移していること | K52: 1.「←図面一覧」を押下する | L52: ・図面一覧画面「リスト」タブに遷移すること ・図面一覧画面の検索条件が保持されていること | N52: 未実施 | O52: 基本的にはOKだが残バグあり | P52: =IF(ISNUMBER(SEARCH("Auto",M52)),"〇","×") -> × | Q52: × | R52: プレビュー⇔リストに切り替え後に図面詳細への遷移では発生します！ →確認済
A53: =A52+1 -> 51 | B53: 図面詳細 (「図面・資料」タブ)_共通 | C53: 図面一覧への戻り遷移 | D53: 再検索 | E53: 検索あり | G53: A | J53: ・図面詳細画面(「図面・資料」タブ)を表示していること ・図面一覧画面から検索ありで遷移していること | K53: 1.「←図面一覧」を押下する 2.詳細絞り込みで再度検索を行う 3,ページング操作を行う | L53: ・詳細絞り込みでの検索内容が正しく表示されること ・ページング操作を正常に行うことができ、図面が正しく表示されていること | N53: 未実施 | P53: =IF(ISNUMBER(SEARCH("Auto",M53)),"〇","×") -> × | Q53: ×
A54: =A53+1 -> 52 | B54: 図面詳細 (「図面・資料」タブ)_共通 | C54: 削除(図面箱) | G54: B | J54: ・図面詳細画面(「図面・資料」タブ)を表示していること | K54: 1.「…」を押下する 2.「削除」を押下する 3."delete"と入力する 4.「削除する」を押下する | L54: ・図面の削除ができること | N54: 未実施 | P54: =IF(ISNUMBER(SEARCH("Auto",M54)),"〇","×") -> × | Q54: ×
A55: =A54+1 -> 53 | B55: 図面詳細 (「図面・資料」タブ)_共通 | C55: 複製 | D55: 新規案件作成なし | G55: A | I55: ※書き込みを行わないパターン | J55: ・図面詳細画面(「図面・資料」タブ)で図面を表示していること | K55: 1.「…」を押下する 2.「複製」を押下する 3.任意に項目を編集する 4.「次へ」を押下する 5.任意の関連資料を選択する 6.「保存する」を押下する 7.「複製した図面に移動する」を押下する | L55: ・図面と関連資料が複製され、新規案件が作成されないこと | N55: 未実施 | P55: =IF(ISNUMBER(SEARCH("Auto",M55)),"〇","×") -> × | Q55: × | T55: 〇
A56: =A55+1 -> 54 | B56: 図面詳細 (「図面・資料」タブ)_共通 | C56: 複製 | D56: 新規案件作成あり | G56: A | I56: ※書き込みを行うパターン | J56: ・図面詳細画面(「図面・資料」タブ)で図面を表示していること | K56: 1.「…」を押下する 2.「複製」を押下する 3.「+書き込み」を押下する 4.任意の内容の書き込みを行う 5.「保存する」を押下する 6.「+ 図面を複製」を押下する 7.任意に項目を編集する 8.「次へ」を押下する 9.任意の関連資料を選択する 10.「新規案件を同時に作成する」のチェックをONにする 11.案件項目に任意の値を入力する 12.「保存する」を押下する 13.「複製した図面に移動する」を押下する | L56: ・図面と関連資料が複製され、新規案件が作成されること ・書き込みを行った図面ファイルが複製先に追加されていること | N56: 未実施 | P56: =IF(ISNUMBER(SEARCH("Auto",M56)),"〇","×") -> × | Q56: × | T56: 〇
A57: =A56+1 -> 55 | B57: 図面詳細 (「図面・資料」タブ)_共通 | C57: アップロード者・日時表示 | G57: A | I57: プレビューの下にも記載あるかも確認。 | J57: ・図面詳細画面(「図面・資料」タブ)を表示していること | K57: 1.「i」を押下する | L57: ・アップロード日時/アップロード者が表示されること | N57: 未実施 | P57: =IF(ISNUMBER(SEARCH("Auto",M57)),"〇","×") -> × | Q57: ×
A58: =A57+1 -> 56 | B58: 図面詳細 (「図面・資料」タブ)_共通 | C58: ファイル名変更 | G58: B | J58: ・図面詳細画面(「図面・資料」タブ)を表示していること | K58: 1.ファイル名を押下する 2.任意の値を入力する 3.「保存」を押下する | L58: ・入力したファイル名に変更できること | N58: 未実施 | P58: =IF(ISNUMBER(SEARCH("Auto",M58)),"〇","×") -> × | Q58: ×
A59: =A58+1 -> 57 | B59: 図面詳細 (「図面・資料」タブ)_共通 | C59: メモ編集 | G59: A | J59: ・図面詳細画面(「図面・資料」タブ)を表示していること | K59: 1.「メモ」を押下する 2.任意の値を入力する 3.「保存」を押下する | L59: ・メモの入力/更新ができること | N59: 未実施 | P59: =IF(ISNUMBER(SEARCH("Auto",M59)),"〇","×") -> × | Q59: ×
A60: =A59+1 -> 58 | B60: 図面詳細 (「図面・資料」タブ)_共通 | C60: 分割・回転 | G60: A | J60: ・図面詳細画面(「図面・資料」タブ)を表示していること | K60: 1.「分割・回転」を押下する 2.任意の変更を行う 3.「保存する」を押下する | L60: ・変更した通りに分割・回転した内容で保存できること | N60: 未実施 | P60: =IF(ISNUMBER(SEARCH("Auto",M60)),"〇","×") -> × | Q60: ×
A61: =A60+1 -> 59 | B61: 図面詳細 (「図面・資料」タブ)_共通 | C61: 拡大表示(ctrl+拡大) | G61: A | I61: タッチパッドではctrl押さなくても拡大される | J61: ・図面詳細画面(「図面・資料」タブ)を表示していること | K61: 1.ファイルのプレビューにピンチイン/ピンチアウト操作を行う | L61: ・拡大/縮小表示ができること | N61: 未実施 | P61: =IF(ISNUMBER(SEARCH("Auto",M61)),"〇","×") -> × | Q61: ×
A62: =A61+1 -> 60 | B62: 図面詳細 (「図面・資料」タブ)_共通 | C62: 類似図面検索 | D62: 検索 | F62: 最新図面しか検索対象ではない。 同じ図面箱は検索対象から外す。 | G62: A | I62: 顧客名がデフォルトで入力されていること | J62: ・図面詳細画面(「図面・資料」タブ)を表示していること | K62: 1.「類似図面」を押下する | L62: ・類似図面が表示されること | N62: 未実施 | P62: =IF(ISNUMBER(SEARCH("Auto",M62)),"〇","×") -> × | Q62: ×
A63: =A62+1 -> 61 | B63: 図面詳細 (「図面・資料」タブ)_共通 | C63: 類似図面検索 | D63: 絞り込み | G63: A | H63: ステータス、顧客名、図番、品名、文字、数値、日付、備考 | J63: 同上 | K63: 2.絞り込み条件を入力/選択する | L63: ・絞り込み条件に一致した類似図面のみ表示されること | N63: 未実施 | P63: =IF(ISNUMBER(SEARCH("Auto",M63)),"〇","×") -> × | Q63: ×
A64: =A63+1 -> 62 | B64: 図面詳細 (「図面・資料」タブ)_共通 | C64: 類似図面検索 | D64: 図面詳細ボタン | G64: A | J64: 同上 | K64: 3.絞り込み結果から任意の図面の「図面詳細」を押下する | L64: ・選択した図面の図面詳細画面が別タブで開くこと | N64: 未実施 | P64: =IF(ISNUMBER(SEARCH("Auto",M64)),"〇","×") -> × | Q64: ×
A65: =A64+1 -> 63 | B65: 図面詳細 (「図面・資料」タブ)_共通 | C65: このファイルの案件 | D65: 新規案件作成 | G65: C | J65: ・図面詳細画面(「図面・資料」タブ)を表示していること | K65: 1.「このファイルの案件」を押下する 2.「新規案件作成」を押下する | L65: ・図面に紐づく新規案件が作成できること | N65: 未実施 | P65: =IF(ISNUMBER(SEARCH("Auto",M65)),"〇","×") -> × | Q65: ×
A66: =A65+1 -> 64 | B66: 図面詳細 (「図面・資料」タブ)_共通 | C66: このファイルの案件 | D66: 案件紐づけ | G66: C | J66: ・図面詳細画面(「図面・資料」タブ)を表示していること | K66: 1.「このファイルの案件」を押下する 2.任意の案件を選択する 3.「保存する」を押下する | L66: ・図面に紐づく案件を変更できること | N66: 未実施 | P66: =IF(ISNUMBER(SEARCH("Auto",M66)),"〇","×") -> × | Q66: ×
A67: =A66+1 -> 65 | B67: 図面詳細 (「図面・資料」タブ)_共通 | C67: 複製 | G67: A | J67: ・図面詳細画面(「図面・資料」タブ)を表示していること | K67: 1.「複製」を押下する 2.任意のファイル名を入力する 3.「複製を保存する」を押下する | L67: ・入力したファイル名でファイルが複製されること | N67: 未実施 | P67: =IF(ISNUMBER(SEARCH("Auto",M67)),"〇","×") -> × | Q67: ×
A68: =A67+1 -> 66 | B68: 図面詳細 (「図面・資料」タブ)_共通 | C68: 書き込み | D68: 拡大/縮小 | G68: A | I68: ※拡張子の指定は要検討 | J68: ・図面詳細画面(「図面・資料」タブ)を表示していること ・2ページ以上あるファイルであること | K68: 1.「書き込み」を押下する 2.ピンチイン/ピンチアウト操作を行う | L68: ・拡大/縮小表示ができること | M68: Auto | N68: 自動化 | O68: 書き込み 手動での簡単な動作確認必要 | P68: =IF(ISNUMBER(SEARCH("Auto",M68)),"〇","×") -> 〇 | Q68: 〇
A69: =A68+1 -> 67 | B69: 図面詳細 (「図面・資料」タブ)_共通 | C69: 書き込み | D69: 直線 | E69: カラー変更 | G69: A | H69: 黒、灰、白、赤、青、緑、黄色、オレンジ、紫 | J69: 同上 | K69: 3.「直線」を押下する 4.任意のカラーを選択する | L69: ・カラーの選択ができること | M69: Auto | N69: 自動化 | P69: =IF(ISNUMBER(SEARCH("Auto",M69)),"〇","×") -> 〇 | Q69: 〇
A70: =A69+1 -> 68 | B70: 図面詳細 (「図面・資料」タブ)_共通 | C70: 書き込み | D70: 直線 | E70: 透明度変更 | G70: A | K70: 5.透明度を任意に変更する | L70: ・透明度の選択ができること | M70: Auto | N70: 自動化 | P70: =IF(ISNUMBER(SEARCH("Auto",M70)),"〇","×") -> 〇 | Q70: 〇
A71: =A70+1 -> 69 | B71: 図面詳細 (「図面・資料」タブ)_共通 | C71: 書き込み | D71: 直線 | E71: 線の太さ変更 | G71: A | H71: 極細、細、中、太 | J71: 同上 | K71: 6.任意の線の太さを選択する | L71: ・線の太さの選択ができること | M71: Auto | N71: 自動化 | P71: =IF(ISNUMBER(SEARCH("Auto",M71)),"〇","×") -> 〇 | Q71: 〇
A72: =A71+1 -> 70 | B72: 図面詳細 (「図面・資料」タブ)_共通 | C72: 書き込み | D72: 直線 | E72: 書き込み | G72: A | J72: 同上 | K72: 7.直線の書き込みを行う | L72: ・選択したカラー、透明度、線の太さで書き込みができること | M72: Auto | N72: 自動化 | P72: =IF(ISNUMBER(SEARCH("Auto",M72)),"〇","×") -> 〇 | Q72: 〇
A73: =A72+1 -> 71 | B73: 図面詳細 (「図面・資料」タブ)_共通 | C73: 書き込み | D73: 直線 | E73: 変更 | G73: A | H73: カラー、線の太さ、透明度 | J73: 同上 | K73: 8.入力確定後の直線を押下する 9.カラー、線の太さを変更する | L73: ・入力確定後の直線のカラー線の太さを変更できること | M73: Auto | N73: 自動化 | P73: =IF(ISNUMBER(SEARCH("Auto",M73)),"〇","×") -> 〇 | Q73: 〇
A74: =A73+1 -> 72 | B74: 図面詳細 (「図面・資料」タブ)_共通 | C74: 書き込み | D74: 矢印 | E74: カラー変更 | G74: A | H74: 黒、灰、白、赤、青、緑、黄色、オレンジ、紫 | J74: 同上 | K74: 10.「矢印」を押下する 11.任意のカラーを選択する | L74: ・カラーの選択ができること | M74: Auto | N74: 自動化 | P74: =IF(ISNUMBER(SEARCH("Auto",M74)),"〇","×") -> 〇 | Q74: 〇
A75: =A74+1 -> 73 | B75: 図面詳細 (「図面・資料」タブ)_共通 | C75: 書き込み | D75: 矢印 | E75: 透明度変更 | G75: A | J75: 同上 | K75: 12.透明度を任意に変更する | L75: ・透明度の選択ができること | M75: Auto | N75: 自動化 | P75: =IF(ISNUMBER(SEARCH("Auto",M75)),"〇","×") -> 〇 | Q75: 〇
A76: =A75+1 -> 74 | B76: 図面詳細 (「図面・資料」タブ)_共通 | C76: 書き込み | D76: 矢印 | E76: 線の太さ変更 | G76: A | J76: 同上 | K76: 13.任意の線の太さを選択する | L76: ・線の太さの選択ができること | M76: Auto | N76: 自動化 | P76: =IF(ISNUMBER(SEARCH("Auto",M76)),"〇","×") -> 〇 | Q76: 〇
A77: =A76+1 -> 75 | B77: 図面詳細 (「図面・資料」タブ)_共通 | C77: 書き込み | D77: 矢印 | E77: 書き込み | G77: A | J77: 同上 | K77: 14.矢印の書き込みを行う | L77: ・選択したカラー、透明度、線の太さで書き込みができること | M77: Auto | N77: 自動化 | P77: =IF(ISNUMBER(SEARCH("Auto",M77)),"〇","×") -> 〇 | Q77: 〇
A78: =A77+1 -> 76 | B78: 図面詳細 (「図面・資料」タブ)_共通 | C78: 書き込み | D78: 矢印 | E78: 変更 | G78: A | H78: カラー、線の太さ | J78: 同上 | K78: 15.入力確定後の矢印を押下する 16.カラー、線の太さを変更する | L78: ・入力確定後の矢印のカラーと線の太さを変更できること | M78: Auto | N78: 自動化 | P78: =IF(ISNUMBER(SEARCH("Auto",M78)),"〇","×") -> 〇 | Q78: 〇
A79: =A78+1 -> 77 | B79: 図面詳細 (「図面・資料」タブ)_共通 | C79: 書き込み | D79: 四角形 | E79: カラー変更 | G79: A | H79: 黒、灰、白、赤、青、緑、黄色、オレンジ、紫 | J79: 同上 | K79: 17.「四角形」を押下する 18.任意のカラーを選択する | L79: ・カラーの選択ができること | M79: Auto | N79: 自動化 | P79: =IF(ISNUMBER(SEARCH("Auto",M79)),"〇","×") -> 〇 | Q79: 〇
A80: =A79+1 -> 78 | B80: 図面詳細 (「図面・資料」タブ)_共通 | C80: 書き込み | D80: 四角形 | E80: 線の太さ変更 | G80: A | H80: 極細、細、中、太 | J80: 同上 | K80: 19.任意の線の太さを選択する | L80: ・線の太さの選択ができること | M80: Auto | N80: 自動化 | P80: =IF(ISNUMBER(SEARCH("Auto",M80)),"〇","×") -> 〇 | Q80: 〇
A81: =A80+1 -> 79 | B81: 図面詳細 (「図面・資料」タブ)_共通 | C81: 書き込み | D81: 四角形 | E81: 塗りつぶし変更 | G81: A | H81: 塗りつぶし有、塗りつぶし無 | J81: 同上 | K81: 20.塗りつぶしのチェックを押下する | L81: ・塗りつぶしのチェックON/OFFの切り替えができること | M81: Auto | N81: 自動化 | P81: =IF(ISNUMBER(SEARCH("Auto",M81)),"〇","×") -> 〇 | Q81: 〇
A82: =A81+1 -> 80 | B82: 図面詳細 (「図面・資料」タブ)_共通 | C82: 書き込み | D82: 四角形 | E82: 書き込み | G82: A | J82: 同上 | K82: 21.四角形の書き込みを行う | L82: ・選択したカラー、線の太さ、塗りつぶしで書き込みができること | M82: Auto | N82: 自動化 | P82: =IF(ISNUMBER(SEARCH("Auto",M82)),"〇","×") -> 〇 | Q82: 〇
A83: =A82+1 -> 81 | B83: 図面詳細 (「図面・資料」タブ)_共通 | C83: 書き込み | D83: 四角形 | E83: 変更 | G83: A | H83: カラー、線の太さ、塗りつぶし | J83: 同上 | K83: 22.入力確定後の四角形を押下する 23.カラー、線の太さ、塗りつぶしを変更する | L83: ・入力確定後の四角形のカラー、線の太さ、塗りつぶしを変更できること | M83: Auto | N83: 自動化 | P83: =IF(ISNUMBER(SEARCH("Auto",M83)),"〇","×") -> 〇 | Q83: 〇
A84: =A83+1 -> 82 | B84: 図面詳細 (「図面・資料」タブ)_共通 | C84: 書き込み | D84: 円形 | E84: カラー変更 | G84: B | H84: 黒、灰、白、赤、青、緑、黄色、オレンジ、紫 | J84: 同上 | K84: 24.「円形」を押下する 25.任意のカラーを選択する | L84: ・カラーの選択ができること | M84: Auto | N84: 自動化 | P84: =IF(ISNUMBER(SEARCH("Auto",M84)),"〇","×") -> 〇 | Q84: 〇
A85: =A84+1 -> 83 | B85: 図面詳細 (「図面・資料」タブ)_共通 | C85: 書き込み | D85: 円形 | E85: 線の太さ変更 | G85: B | H85: 極細、細、中、太 | J85: 同上 | K85: 26.任意の線の太さを選択する | L85: ・線の太さの選択ができること | M85: Auto | N85: 自動化 | P85: =IF(ISNUMBER(SEARCH("Auto",M85)),"〇","×") -> 〇 | Q85: 〇
A86: =A85+1 -> 84 | B86: 図面詳細 (「図面・資料」タブ)_共通 | C86: 書き込み | D86: 円形 | E86: 塗りつぶし変更 | G86: B | H86: 塗りつぶし有、塗りつぶし無 | J86: 同上 | K86: 27.塗りつぶしのチェックを押下する | L86: ・塗りつぶしのチェックON/OFFの切り替えができること | M86: Auto | N86: 自動化 | P86: =IF(ISNUMBER(SEARCH("Auto",M86)),"〇","×") -> 〇 | Q86: 〇
A87: =A86+1 -> 85 | B87: 図面詳細 (「図面・資料」タブ)_共通 | C87: 書き込み | D87: 円形 | E87: 書き込み | G87: A | J87: 同上 | K87: 28.四角形の書き込みを行う | L87: ・選択したカラー、線の太さ、塗りつぶしで書き込みができること | M87: Auto | N87: 自動化 | P87: =IF(ISNUMBER(SEARCH("Auto",M87)),"〇","×") -> 〇 | Q87: 〇
A88: =A87+1 -> 86 | B88: 図面詳細 (「図面・資料」タブ)_共通 | C88: 書き込み | D88: 円形 | E88: 変更 | G88: A | H88: カラー、線の太さ、塗りつぶし | J88: 同上 | K88: 29.入力確定後の四角形を押下する 30.カラー、線の太さ、塗りつぶしを変更する | L88: ・入力確定後の円形のカラー、線の太さ、塗りつぶしを変更できること | M88: Auto | N88: 自動化 | P88: =IF(ISNUMBER(SEARCH("Auto",M88)),"〇","×") -> 〇 | Q88: 〇
A89: =A88+1 -> 87 | B89: 図面詳細 (「図面・資料」タブ)_共通 | C89: 書き込み | D89: ペン | E89: カラー変更 | G89: A | H89: 黒、灰、白、赤、青、緑、黄色、オレンジ、紫 | J89: 同上 | K89: 31.「ペン」を押下する 32.任意のカラーを選択する | L89: ・カラーの選択ができること | M89: Auto | N89: 自動化 | P89: =IF(ISNUMBER(SEARCH("Auto",M89)),"〇","×") -> 〇 | Q89: 〇
A90: =A89+1 -> 88 | B90: 図面詳細 (「図面・資料」タブ)_共通 | C90: 書き込み | D90: ペン | E90: 線の太さ変更 | G90: A | H90: 極細、細、中、太 | J90: 同上 | K90: 33.任意の線の太さを選択する | L90: ・線の太さの選択ができること | M90: Auto | N90: 自動化 | P90: =IF(ISNUMBER(SEARCH("Auto",M90)),"〇","×") -> 〇 | Q90: 〇
A91: =A90+1 -> 89 | B91: 図面詳細 (「図面・資料」タブ)_共通 | C91: 書き込み | D91: ペン | E91: 書き込み | G91: A | J91: 同上 | K91: 34.ペンの書き込みを行う | L91: ・選択したカラーと線の太さで書き込みができること | M91: Auto | N91: 自動化 | P91: =IF(ISNUMBER(SEARCH("Auto",M91)),"〇","×") -> 〇 | Q91: 〇
A92: =A91+1 -> 90 | B92: 図面詳細 (「図面・資料」タブ)_共通 | C92: 書き込み | D92: ペン | E92: 消しゴム | G92: A | I92: ※書き込み途中以外のオブジェクトに対しては消しゴム機能は使えない | J92: 同上 | K92: 35.消しゴムを押下する 36.任意の太さを選択する 37.書き込み箇所を消す | L92: ・書き込み途中のペンオブジェクトを消せること | M92: Auto | N92: 自動化 | P92: =IF(ISNUMBER(SEARCH("Auto",M92)),"〇","×") -> 〇 | Q92: 〇
A93: =A92+1 -> 91 | B93: 図面詳細 (「図面・資料」タブ)_共通 | C93: 書き込み | D93: ペン | E93: 変更 | G93: A | H93: カラー、線の太さ | J93: 同上 | K93: 38.入力確定後のペンの書き込みを押下する 39.カラー、線の太さを変更する | L93: ・入力確定後のペンの書き込みのカラー、線の太さを変更できること | M93: Auto | N93: 自動化 | P93: =IF(ISNUMBER(SEARCH("Auto",M93)),"〇","×") -> 〇 | Q93: 〇
A94: =A93+1 -> 92 | B94: 図面詳細 (「図面・資料」タブ)_共通 | C94: 書き込み | D94: マーカー | E94: カラー変更 | G94: A | H94: 黄、緑、ピンク、シアン、ピーチ、ラベンダー | J94: 同上 | K94: 40.「マーカー」を押下する 41.任意のカラーを選択する | L94: ・カラーの選択ができること | M94: Auto | N94: 自動化 | P94: =IF(ISNUMBER(SEARCH("Auto",M94)),"〇","×") -> 〇 | Q94: 〇
A95: =A94+1 -> 93 | B95: 図面詳細 (「図面・資料」タブ)_共通 | C95: 書き込み | D95: マーカー | E95: 線の太さ変更 | G95: A | H95: 通常、太、極太 | J95: 同上 | K95: 42.任意の線の太さを選択する | L95: ・線の太さの選択ができること | M95: Auto | N95: 自動化 | P95: =IF(ISNUMBER(SEARCH("Auto",M95)),"〇","×") -> 〇 | Q95: 〇
A96: =A95+1 -> 94 | B96: 図面詳細 (「図面・資料」タブ)_共通 | C96: 書き込み | D96: マーカー | E96: 書き込み | G96: A | J96: 同上 | K96: 43.マーカーの書き込みを行う | L96: ・選択したカラーと線の太さで書き込みができること | M96: Auto | N96: 自動化 | P96: =IF(ISNUMBER(SEARCH("Auto",M96)),"〇","×") -> 〇 | Q96: 〇
A97: =A96+1 -> 95 | B97: 図面詳細 (「図面・資料」タブ)_共通 | C97: 書き込み | D97: マーカー | E97: 消しゴム | G97: A | I97: ※書き込み途中以外のオブジェクトに対しては消しゴム機能は使えない | J97: 同上 | K97: 44.消しゴムを押下する 45.任意の太さを選択する 46.書き込み箇所を消す | L97: ・書き込み途中のマーカーオブジェクトを消せること | M97: Auto | N97: 自動化 | P97: =IF(ISNUMBER(SEARCH("Auto",M97)),"〇","×") -> 〇 | Q97: 〇
A98: =A97+1 -> 96 | B98: 図面詳細 (「図面・資料」タブ)_共通 | C98: 書き込み | D98: マーカー | E98: 変更 | G98: A | H98: カラー、線の太さ | J98: 同上 | K98: 47.入力確定後のマーカーの書き込みを押下する 48.カラー、線の太さを変更する | L98: ・入力確定後のマーカーの書き込みのカラー、線の太さを変更できること | M98: Auto | N98: 自動化 | P98: =IF(ISNUMBER(SEARCH("Auto",M98)),"〇","×") -> 〇 | Q98: 〇
A99: =A98+1 -> 97 | B99: 図面詳細 (「図面・資料」タブ)_共通 | C99: 書き込み | D99: テキスト | E99: カラー変更 | G99: A | H99: 黒、灰、白、赤、青、緑、黄色、オレンジ、紫 | J99: 同上 | K99: 49.「テキスト」を押下する 50.任意のカラーを選択する | L99: ・カラーの選択ができること | M99: Auto | N99: 自動化 | P99: =IF(ISNUMBER(SEARCH("Auto",M99)),"〇","×") -> 〇 | Q99: 〇
A100: =A99+1 -> 98 | B100: 図面詳細 (「図面・資料」タブ)_共通 | C100: 書き込み | D100: テキスト | E100: 文字サイズ変更 | G100: A | H100: 4、6、8、12、14、16、18、24、28、32、48、64 | J100: 同上 | K100: 51.任意の文字サイズを選択する | L100: ・文字サイズの選択ができること | M100: Auto | N100: 自動化 | P100: =IF(ISNUMBER(SEARCH("Auto",M100)),"〇","×") -> 〇 | Q100: 〇
...

Sheet 0823向け修正メモ
A1: チケット | B1: URL | C1: 追加済チェック
A2: 顧客名の「正式名称」を持てるようにする | B2: https://app.notion.com/p/fact-base/3a77b39bb0c8818dbb2bddd161c01e80 | C2: 済
A3: 書き込み：案件一覧で連続書き込み | B3: https://app.notion.com/p/fact-base/3a47b39bb0c880c18f04f77957e8cd11 | C3: 済
A22: ※動作上変わらないチケットは記載対象外

Sheet 集計
B1: ケース数
B3: A | C3: B | D3: C | E3: D | F3: 計
B4: =COUNTIF('機能一覧'!$G:$G,B3) -> 356 | C4: =COUNTIF('機能一覧'!$G:$G,C3) -> 109 | D4: =COUNTIF('機能一覧'!$G:$G,D3) -> 18 | E4: =COUNTIF('機能一覧'!$G:$G,E3) -> 43 | F4: =SUM(B4:E4) -> 526
B6: 実施結果
B8: ステータス | C8: A | D8: B | E8: C | F8: D | G8: 計
B9: 未実施 | C9: =COUNTIFS('機能一覧'!$G$3:$G$627,'集計'!C$8,'機能一覧'!$N$3:$N$627,'集計'!$B9) -> 234 | D9: =COUNTIFS('機能一覧'!$G$3:$G$627,'集計'!D$8,'機能一覧'!$N$3:$N$627,'集計'!$B9) -> 45 | E9: =COUNTIFS('機能一覧'!$G$3:$G$627,'集計'!E$8,'機能一覧'!$N$3:$N$627,'集計'!$B9) -> 7 | F9: =COUNTIFS('機能一覧'!$G$3:$G$627,'集計'!F$8,'機能一覧'!$N$3:$N$627,'集計'!$B9) -> 43 | G9: =SUM(C9:F9) -> 329
B10: OK | C10: =COUNTIFS('機能一覧'!$G$3:$G$627,'集計'!C$8,'機能一覧'!$N$3:$N$627,'集計'!$B10) -> 0 | D10: =COUNTIFS('機能一覧'!$G$3:$G$627,'集計'!D$8,'機能一覧'!$N$3:$N$627,'集計'!$B10) -> 0 | E10: =COUNTIFS('機能一覧'!$G$3:$G$627,'集計'!E$8,'機能一覧'!$N$3:$N$627,'集計'!$B10) -> 0 | F10: =COUNTIFS('機能一覧'!$G$3:$G$627,'集計'!F$8,'機能一覧'!$N$3:$N$627,'集計'!$B10) -> 0 | G10: =SUM(C10:F10) -> 0
B11: NG | C11: =COUNTIFS('機能一覧'!$G$3:$G$627,'集計'!C$8,'機能一覧'!$N$3:$N$627,'集計'!$B11) -> 0 | D11: =COUNTIFS('機能一覧'!$G$3:$G$627,'集計'!D$8,'機能一覧'!$N$3:$N$627,'集計'!$B11) -> 0 | E11: =COUNTIFS('機能一覧'!$G$3:$G$627,'集計'!E$8,'機能一覧'!$N$3:$N$627,'集計'!$B11) -> 0 | F11: =COUNTIFS('機能一覧'!$G$3:$G$627,'集計'!F$8,'機能一覧'!$N$3:$N$627,'集計'!$B11) -> 0 | G11: =SUM(C11:F11) -> 0
B12: 保留 | C12: =COUNTIFS('機能一覧'!$G$3:$G$627,'集計'!C$8,'機能一覧'!$N$3:$N$627,'集計'!$B12) -> 0 | D12: =COUNTIFS('機能一覧'!$G$3:$G$627,'集計'!D$8,'機能一覧'!$N$3:$N$627,'集計'!$B12) -> 0 | E12: =COUNTIFS('機能一覧'!$G$3:$G$627,'集計'!E$8,'機能一覧'!$N$3:$N$627,'集計'!$B12) -> 0 | F12: =COUNTIFS('機能一覧'!$G$3:$G$627,'集計'!F$8,'機能一覧'!$N$3:$N$627,'集計'!$B12) -> 0 | G12: =SUM(C12:F12) -> 0
B13: 対象外 | C13: =COUNTIFS('機能一覧'!$G$3:$G$627,'集計'!C$8,'機能一覧'!$N$3:$N$627,'集計'!$B13) -> 0 | D13: =COUNTIFS('機能一覧'!$G$3:$G$627,'集計'!D$8,'機能一覧'!$N$3:$N$627,'集計'!$B13) -> 0 | E13: =COUNTIFS('機能一覧'!$G$3:$G$627,'集計'!E$8,'機能一覧'!$N$3:$N$627,'集計'!$B13) -> 0 | F13: =COUNTIFS('機能一覧'!$G$3:$G$627,'集計'!F$8,'機能一覧'!$N$3:$N$627,'集計'!$B13) -> 0 | G13: =SUM(C13:F13) -> 0
B14: 自動化 | C14: =COUNTIFS('機能一覧'!$G$3:$G$627,'集計'!C$8,'機能一覧'!$N$3:$N$627,'集計'!$B14) -> 122 | D14: =COUNTIFS('機能一覧'!$G$3:$G$627,'集計'!D$8,'機能一覧'!$N$3:$N$627,'集計'!$B14) -> 64 | E14: =COUNTIFS('機能一覧'!$G$3:$G$627,'集計'!E$8,'機能一覧'!$N$3:$N$627,'集計'!$B14) -> 11 | F14: =COUNTIFS('機能一覧'!$G$3:$G$627,'集計'!F$8,'機能一覧'!$N$3:$N$627,'集計'!$B14) -> 0 | G14: =SUM(C14:F14) -> 197
